napari_yapic_prediction/__init__.py
napari_yapic_prediction/_dock_widget.py
napari_yapic_prediction/yapic_dependencies.py
napari_yapic_prediction/yapic_prediction.py
napari_yapic_prediction/_tests/__init__.py
napari_yapic_prediction/_tests/test_dock_widget.py
napari_yapic_prediction-0.2.0.dist-info/LICENSE
napari_yapic_prediction-0.2.0.dist-info/METADATA
napari_yapic_prediction-0.2.0.dist-info/WHEEL
napari_yapic_prediction-0.2.0.dist-info/entry_points.txt
napari_yapic_prediction-0.2.0.dist-info/top_level.txt
napari_yapic_prediction-0.2.0.dist-info/RECORD
