Metadata-Version: 2.1
Name: napari-yapic-prediction
Version: 0.2.0
Summary: napari widget that performs image segmentation with yapic model in the napari window. Install TENSORFLOW to use this plugin.
Home-page: https://github.com/yapic/napari-yapic-prediction
Author: Duway Nicolas Lesmes Leon, Pranjal Dhole
Author-email: dlesmesleon@hotmail.com, dhole.pranjal@gmail.com
License: GNU GPL v3.0
Platform: UNKNOWN
Classifier: Development Status :: 4 - Beta
Classifier: Intended Audience :: Developers
Classifier: Framework :: napari
Classifier: Topic :: Software Development :: Testing
Classifier: Programming Language :: Python
Classifier: Programming Language :: Python :: 3
Classifier: Programming Language :: Python :: 3.7
Classifier: Programming Language :: Python :: 3.8
Classifier: Operating System :: OS Independent
Classifier: License :: OSI Approved :: GNU General Public License v3 (GPLv3)
Requires-Python: >=3.6
License-File: LICENSE
Requires-Dist: napari-plugin-engine (>=0.1.4)
Requires-Dist: numpy
Requires-Dist: napari[all]
Requires-Dist: yapic
Requires-Dist: scikit-image
